{"https_enforcer_enabled": false, "wifi_repeater": {"chipset": "", "password": "12345678", "ssid": "fqrouter"}, "tcp_gateway": {"ip": "", "enabled": false, "port": 12345}, "upnp": {"username": "", "is_password_protected": false, "password": "", "port": 25}, "http_manager": {"ip": "", "enabled": true, "port": 2515}, "direct_access_enabled": false, "china_shortcut_enabled": true, "public_servers": {"goagent_enabled": false, "source": "no_available_source!", "ss_enabled": false}, "http_gateway": {"ip": "", "enabled": false, "port": 2516}, "google_scrambler_enabled": false, "tcp_scrambler_enabled": false, "config_file": "/data/data/net.xndroid/files/xndroid_files/fqrouter/etc/fqsocks.json", "private_servers": {"0304ab98-6eed-444c-8405-8917ec3a6dcf": {"username": "", "proxy_type": "HTTP", "host": "127.0.0.1", "transport_type": "HTTP", "traffic_type": "HTTP/HTTPS", "password": "", "port": 8087}}, "hosted_domain_enabled": false, "prefers_private_proxy": true, "access_check_enabled": true, "dns_server": {"ip": "", "enabled": false, "port": 12345}}